libauc/__init__.py
libauc/datasets/__init__.py
libauc/datasets/breastcancer.py
libauc/datasets/cat_vs_dog.py
libauc/datasets/chexpert.py
libauc/datasets/cifar.py
libauc/datasets/dataset.py
libauc/datasets/folder.py
libauc/datasets/melanoma.py
libauc/datasets/movielens.py
libauc/datasets/musk2.py
libauc/datasets/stl10.py
libauc/datasets/webdataset.py
libauc/losses/__init__.py
libauc/losses/auc.py
libauc/losses/contrastive.py
libauc/losses/losses.py
libauc/losses/mil.py
libauc/losses/perf_at_top.py
libauc/losses/ranking.py
libauc/losses/surrogate.py
libauc/metrics/__init__.py
libauc/metrics/metrics.py
libauc/metrics/metrics_k.py
libauc/models/__init__.py
libauc/models/densenet.py
libauc/models/gnn.py
libauc/models/mil_models.py
libauc/models/neumf.py
libauc/models/perceptron.py
libauc/models/resnet.py
libauc/models/resnet_cifar.py
libauc/optimizers/__init__.py
libauc/optimizers/adam.py
libauc/optimizers/adamw.py
libauc/optimizers/isogclr.py
libauc/optimizers/lars.py
libauc/optimizers/midam.py
libauc/optimizers/pdsca.py
libauc/optimizers/pesg.py
libauc/optimizers/sgd.py
libauc/optimizers/soap.py
libauc/optimizers/sogclr.py
libauc/optimizers/song.py
libauc/optimizers/sopa.py
libauc/optimizers/sopa_s.py
libauc/optimizers/sota_s.py
libauc/sampler/__init__.py
libauc/sampler/sampler.py
libauc/utils/__init__.py
libauc/utils/paper_utils.py
libauc/utils/utils.py
libauc-1.4.0.dist-info/LICENSE
libauc-1.4.0.dist-info/METADATA
libauc-1.4.0.dist-info/WHEEL
libauc-1.4.0.dist-info/top_level.txt
libauc-1.4.0.dist-info/RECORD
