Metadata-Version: 2.1
Name: libauc
Version: 1.4.0
Summary: LibAUC: A Deep Learning Library for X-Risk Optimization
Home-page: https://github.com/Optimization-AI/LibAUC
Author: Zhuoning Yuan, Tianbao Yang
Classifier: Programming Language :: Python :: 3
Classifier: License :: OSI Approved :: MIT License
Classifier: Operating System :: OS Independent
Requires-Python: >=3.8
License-File: LICENSE
Requires-Dist: torch
Requires-Dist: torchvision
Requires-Dist: numpy
Requires-Dist: tqdm
Requires-Dist: scipy
Requires-Dist: pandas
Requires-Dist: Pillow
Requires-Dist: scikit-learn
Requires-Dist: opencv-python
Requires-Dist: torch-geometric
Requires-Dist: ogb
Requires-Dist: webdataset
